{
    "{\"min_escape_time\": 80, \"min_market_pnl\": 36.0, \"start_echappee_threshold\": 1.5, \"stop_echappee_threshold\": 1, \"take_profit_market_pnl\": 75.0, \"top_n_threshold\": 1, \"trade_interval_minutes\": 150000, \"trade_value_eur\": 100.0, \"trail_stop_market_pnl\": 40}": {
        "total_pnl": 568.1150992065668,
        "total_invested_capital": 8417.761258140206,
        "total_roi": 6.749004655569007,
        "daily_pnl_std": 18.814867294858402,
        "positive_or_zero_pnl_days": 21,
        "negative_pnl_days": 3
    },
    "{\"min_escape_time\": 0, \"min_market_pnl\": 36.0, \"start_echappee_threshold\": 1.5, \"stop_echappee_threshold\": 1, \"take_profit_market_pnl\": 75.0, \"top_n_threshold\": 1, \"trade_interval_minutes\": 150000, \"trade_value_eur\": 100.0, \"trail_stop_market_pnl\": 40}": {
        "total_pnl": 435.90108565986156,
        "total_invested_capital": 10444.940749645233,
        "total_roi": 4.173322722531165,
        "daily_pnl_std": 27.170044107938306,
        "positive_or_zero_pnl_days": 18,
        "negative_pnl_days": 6
    },
    "{\"min_escape_time\": 5, \"min_market_pnl\": 36.0, \"start_echappee_threshold\": 1.5, \"stop_echappee_threshold\": 1, \"take_profit_market_pnl\": 75.0, \"top_n_threshold\": 1, \"trade_interval_minutes\": 150000, \"trade_value_eur\": 100.0, \"trail_stop_market_pnl\": 40}": {
        "total_pnl": 408.5293080955744,
        "total_invested_capital": 10128.964817225933,
        "total_roi": 4.03327798513827,
        "daily_pnl_std": 26.431464276148024,
        "positive_or_zero_pnl_days": 18,
        "negative_pnl_days": 6
    },
    "{\"min_escape_time\": 10, \"min_market_pnl\": 36.0, \"start_echappee_threshold\": 1.5, \"stop_echappee_threshold\": 1, \"take_profit_market_pnl\": 75.0, \"top_n_threshold\": 1, \"trade_interval_minutes\": 150000, \"trade_value_eur\": 100.0, \"trail_stop_market_pnl\": 40}": {
        "total_pnl": 374.2680210918188,
        "total_invested_capital": 9944.288761466742,
        "total_roi": 3.763647959842789,
        "daily_pnl_std": 27.6285723744317,
        "positive_or_zero_pnl_days": 18,
        "negative_pnl_days": 6
    },
    "{\"min_escape_time\": 15, \"min_market_pnl\": 36.0, \"start_echappee_threshold\": 1.5, \"stop_echappee_threshold\": 1, \"take_profit_market_pnl\": 75.0, \"top_n_threshold\": 1, \"trade_interval_minutes\": 150000, \"trade_value_eur\": 100.0, \"trail_stop_market_pnl\": 40}": {
        "total_pnl": 431.1469539254904,
        "total_invested_capital": 9641.325421065092,
        "total_roi": 4.471863930487069,
        "daily_pnl_std": 23.574540944534604,
        "positive_or_zero_pnl_days": 19,
        "negative_pnl_days": 5
    },
    "{\"min_escape_time\": 20, \"min_market_pnl\": 36.0, \"start_echappee_threshold\": 1.5, \"stop_echappee_threshold\": 1, \"take_profit_market_pnl\": 75.0, \"top_n_threshold\": 1, \"trade_interval_minutes\": 150000, \"trade_value_eur\": 100.0, \"trail_stop_market_pnl\": 40}": {
        "total_pnl": 419.68721121549606,
        "total_invested_capital": 9639.401452615857,
        "total_roi": 4.353872107916048,
        "daily_pnl_std": 23.191142981549802,
        "positive_or_zero_pnl_days": 18,
        "negative_pnl_days": 6
    },
    "{\"min_escape_time\": 25, \"min_market_pnl\": 36.0, \"start_echappee_threshold\": 1.5, \"stop_echappee_threshold\": 1, \"take_profit_market_pnl\": 75.0, \"top_n_threshold\": 1, \"trade_interval_minutes\": 150000, \"trade_value_eur\": 100.0, \"trail_stop_market_pnl\": 40}": {
        "total_pnl": 406.5922684520483,
        "total_invested_capital": 9648.273101262748,
        "total_roi": 4.214145517904487,
        "daily_pnl_std": 22.89595934307278,
        "positive_or_zero_pnl_days": 18,
        "negative_pnl_days": 6
    },
    "{\"min_escape_time\": 30, \"min_market_pnl\": 36.0, \"start_echappee_threshold\": 1.5, \"stop_echappee_threshold\": 1, \"take_profit_market_pnl\": 75.0, \"top_n_threshold\": 1, \"trade_interval_minutes\": 150000, \"trade_value_eur\": 100.0, \"trail_stop_market_pnl\": 40}": {
        "total_pnl": 419.3726230710745,
        "total_invested_capital": 9457.978052936494,
        "total_roi": 4.4340621295993445,
        "daily_pnl_std": 20.73974994283955,
        "positive_or_zero_pnl_days": 18,
        "negative_pnl_days": 6
    },
    "{\"min_escape_time\": 35, \"min_market_pnl\": 36.0, \"start_echappee_threshold\": 1.5, \"stop_echappee_threshold\": 1, \"take_profit_market_pnl\": 75.0, \"top_n_threshold\": 1, \"trade_interval_minutes\": 150000, \"trade_value_eur\": 100.0, \"trail_stop_market_pnl\": 40}": {
        "total_pnl": 405.994427010417,
        "total_invested_capital": 9361.779243968427,
        "total_roi": 4.336722928731626,
        "daily_pnl_std": 20.175083206657977,
        "positive_or_zero_pnl_days": 18,
        "negative_pnl_days": 6
    },
    "{\"min_escape_time\": 40, \"min_market_pnl\": 36.0, \"start_echappee_threshold\": 1.5, \"stop_echappee_threshold\": 1, \"take_profit_market_pnl\": 75.0, \"top_n_threshold\": 1, \"trade_interval_minutes\": 150000, \"trade_value_eur\": 100.0, \"trail_stop_market_pnl\": 40}": {
        "total_pnl": 421.7158713489771,
        "total_invested_capital": 9264.34454651922,
        "total_roi": 4.552031384750508,
        "daily_pnl_std": 19.71479758754823,
        "positive_or_zero_pnl_days": 18,
        "negative_pnl_days": 6
    },
    "{\"min_escape_time\": 45, \"min_market_pnl\": 36.0, \"start_echappee_threshold\": 1.5, \"stop_echappee_threshold\": 1, \"take_profit_market_pnl\": 75.0, \"top_n_threshold\": 1, \"trade_interval_minutes\": 150000, \"trade_value_eur\": 100.0, \"trail_stop_market_pnl\": 40}": {
        "total_pnl": 455.23774944245815,
        "total_invested_capital": 9055.776321850717,
        "total_roi": 5.027042776487459,
        "daily_pnl_std": 20.214481610437577,
        "positive_or_zero_pnl_days": 20,
        "negative_pnl_days": 4
    },
    "{\"min_escape_time\": 50, \"min_market_pnl\": 36.0, \"start_echappee_threshold\": 1.5, \"stop_echappee_threshold\": 1, \"take_profit_market_pnl\": 75.0, \"top_n_threshold\": 1, \"trade_interval_minutes\": 150000, \"trade_value_eur\": 100.0, \"trail_stop_market_pnl\": 40}": {
        "total_pnl": 480.1289946138859,
        "total_invested_capital": 9050.569469697773,
        "total_roi": 5.304958944532789,
        "daily_pnl_std": 20.225347560338957,
        "positive_or_zero_pnl_days": 20,
        "negative_pnl_days": 4
    },
    "{\"min_escape_time\": 55, \"min_market_pnl\": 36.0, \"start_echappee_threshold\": 1.5, \"stop_echappee_threshold\": 1, \"take_profit_market_pnl\": 75.0, \"top_n_threshold\": 1, \"trade_interval_minutes\": 150000, \"trade_value_eur\": 100.0, \"trail_stop_market_pnl\": 40}": {
        "total_pnl": 509.3172746896744,
        "total_invested_capital": 8815.575586266816,
        "total_roi": 5.777470452219876,
        "daily_pnl_std": 20.961662125812218,
        "positive_or_zero_pnl_days": 21,
        "negative_pnl_days": 3
    },
    "{\"min_escape_time\": 60, \"min_market_pnl\": 36.0, \"start_echappee_threshold\": 1.5, \"stop_echappee_threshold\": 1, \"take_profit_market_pnl\": 75.0, \"top_n_threshold\": 1, \"trade_interval_minutes\": 150000, \"trade_value_eur\": 100.0, \"trail_stop_market_pnl\": 40}": {
        "total_pnl": 579.9951296076179,
        "total_invested_capital": 8562.63459457457,
        "total_roi": 6.773559273160068,
        "daily_pnl_std": 19.010211946176252,
        "positive_or_zero_pnl_days": 22,
        "negative_pnl_days": 2
    },
    "{\"min_escape_time\": 65, \"min_market_pnl\": 36.0, \"start_echappee_threshold\": 1.5, \"stop_echappee_threshold\": 1, \"take_profit_market_pnl\": 75.0, \"top_n_threshold\": 1, \"trade_interval_minutes\": 150000, \"trade_value_eur\": 100.0, \"trail_stop_market_pnl\": 40}": {
        "total_pnl": 579.21699937433,
        "total_invested_capital": 8539.497965708375,
        "total_roi": 6.782799196161907,
        "daily_pnl_std": 19.694087622870942,
        "positive_or_zero_pnl_days": 21,
        "negative_pnl_days": 3
    },
    "{\"min_escape_time\": 70, \"min_market_pnl\": 36.0, \"start_echappee_threshold\": 1.5, \"stop_echappee_threshold\": 1, \"take_profit_market_pnl\": 75.0, \"top_n_threshold\": 1, \"trade_interval_minutes\": 150000, \"trade_value_eur\": 100.0, \"trail_stop_market_pnl\": 40}": {
        "total_pnl": 569.7680491656065,
        "total_invested_capital": 8547.3508169353,
        "total_roi": 6.666019230621681,
        "daily_pnl_std": 20.24861504041919,
        "positive_or_zero_pnl_days": 19,
        "negative_pnl_days": 5
    },
    "{\"min_escape_time\": 75, \"min_market_pnl\": 36.0, \"start_echappee_threshold\": 1.5, \"stop_echappee_threshold\": 1, \"take_profit_market_pnl\": 75.0, \"top_n_threshold\": 1, \"trade_interval_minutes\": 150000, \"trade_value_eur\": 100.0, \"trail_stop_market_pnl\": 40}": {
        "total_pnl": 548.5830882638693,
        "total_invested_capital": 8524.032230556011,
        "total_roi": 6.435722829594298,
        "daily_pnl_std": 19.376528286763936,
        "positive_or_zero_pnl_days": 21,
        "negative_pnl_days": 3
    },
    "{\"min_escape_time\": 85, \"min_market_pnl\": 36.0, \"start_echappee_threshold\": 1.5, \"stop_echappee_threshold\": 1, \"take_profit_market_pnl\": 75.0, \"top_n_threshold\": 1, \"trade_interval_minutes\": 150000, \"trade_value_eur\": 100.0, \"trail_stop_market_pnl\": 40}": {
        "total_pnl": 514.8540622740984,
        "total_invested_capital": 8427.221892751753,
        "total_roi": 6.109416232613075,
        "daily_pnl_std": 18.8457534991317,
        "positive_or_zero_pnl_days": 22,
        "negative_pnl_days": 2
    },
    "{\"min_escape_time\": 90, \"min_market_pnl\": 36.0, \"start_echappee_threshold\": 1.5, \"stop_echappee_threshold\": 1, \"take_profit_market_pnl\": 75.0, \"top_n_threshold\": 1, \"trade_interval_minutes\": 150000, \"trade_value_eur\": 100.0, \"trail_stop_market_pnl\": 40}": {
        "total_pnl": 511.849951967597,
        "total_invested_capital": 8330.465406753123,
        "total_roi": 6.144313996582519,
        "daily_pnl_std": 18.186253468193286,
        "positive_or_zero_pnl_days": 21,
        "negative_pnl_days": 3
    },
    "{\"min_escape_time\": 95, \"min_market_pnl\": 36.0, \"start_echappee_threshold\": 1.5, \"stop_echappee_threshold\": 1, \"take_profit_market_pnl\": 75.0, \"top_n_threshold\": 1, \"trade_interval_minutes\": 150000, \"trade_value_eur\": 100.0, \"trail_stop_market_pnl\": 40}": {
        "total_pnl": 522.8648306876421,
        "total_invested_capital": 8235.791334874928,
        "total_roi": 6.348689633181224,
        "daily_pnl_std": 18.10071028491025,
        "positive_or_zero_pnl_days": 22,
        "negative_pnl_days": 2
    },
    "{\"min_escape_time\": 100, \"min_market_pnl\": 36.0, \"start_echappee_threshold\": 1.5, \"stop_echappee_threshold\": 1, \"take_profit_market_pnl\": 75.0, \"top_n_threshold\": 1, \"trade_interval_minutes\": 150000, \"trade_value_eur\": 100.0, \"trail_stop_market_pnl\": 40}": {
        "total_pnl": 520.0261467546225,
        "total_invested_capital": 8234.105120696127,
        "total_roi": 6.315515033291905,
        "daily_pnl_std": 17.731988962229096,
        "positive_or_zero_pnl_days": 20,
        "negative_pnl_days": 4
    },
    "{\"min_escape_time\": 105, \"min_market_pnl\": 36.0, \"start_echappee_threshold\": 1.5, \"stop_echappee_threshold\": 1, \"take_profit_market_pnl\": 75.0, \"top_n_threshold\": 1, \"trade_interval_minutes\": 150000, \"trade_value_eur\": 100.0, \"trail_stop_market_pnl\": 40}": {
        "total_pnl": 534.0514357537031,
        "total_invested_capital": 8033.9967837408185,
        "total_roi": 6.647394194064342,
        "daily_pnl_std": 19.39209819489178,
        "positive_or_zero_pnl_days": 20,
        "negative_pnl_days": 4
    },
    "{\"min_escape_time\": 110, \"min_market_pnl\": 36.0, \"start_echappee_threshold\": 1.5, \"stop_echappee_threshold\": 1, \"take_profit_market_pnl\": 75.0, \"top_n_threshold\": 1, \"trade_interval_minutes\": 150000, \"trade_value_eur\": 100.0, \"trail_stop_market_pnl\": 40}": {
        "total_pnl": 513.518534168601,
        "total_invested_capital": 8036.704388029873,
        "total_roi": 6.389665581496964,
        "daily_pnl_std": 18.77379938023773,
        "positive_or_zero_pnl_days": 21,
        "negative_pnl_days": 3
    },
    "{\"min_escape_time\": 115, \"min_market_pnl\": 36.0, \"start_echappee_threshold\": 1.5, \"stop_echappee_threshold\": 1, \"take_profit_market_pnl\": 75.0, \"top_n_threshold\": 1, \"trade_interval_minutes\": 150000, \"trade_value_eur\": 100.0, \"trail_stop_market_pnl\": 40}": {
        "total_pnl": 491.9413852840662,
        "total_invested_capital": 7938.741983748972,
        "total_roi": 6.19671714096637,
        "daily_pnl_std": 18.46399930190958,
        "positive_or_zero_pnl_days": 21,
        "negative_pnl_days": 3
    },
    "{\"min_escape_time\": 120, \"min_market_pnl\": 36.0, \"start_echappee_threshold\": 1.5, \"stop_echappee_threshold\": 1, \"take_profit_market_pnl\": 75.0, \"top_n_threshold\": 1, \"trade_interval_minutes\": 150000, \"trade_value_eur\": 100.0, \"trail_stop_market_pnl\": 40}": {
        "total_pnl": 447.04996402561665,
        "total_invested_capital": 7895.372600384057,
        "total_roi": 5.662176906050902,
        "daily_pnl_std": 18.081635633081092,
        "positive_or_zero_pnl_days": 21,
        "negative_pnl_days": 3
    },
    "{\"min_escape_time\": 125, \"min_market_pnl\": 36.0, \"start_echappee_threshold\": 1.5, \"stop_echappee_threshold\": 1, \"take_profit_market_pnl\": 75.0, \"top_n_threshold\": 1, \"trade_interval_minutes\": 150000, \"trade_value_eur\": 100.0, \"trail_stop_market_pnl\": 40}": {
        "total_pnl": 447.05399702489376,
        "total_invested_capital": 7905.348174609244,
        "total_roi": 5.655082953344953,
        "daily_pnl_std": 17.80348009689034,
        "positive_or_zero_pnl_days": 22,
        "negative_pnl_days": 2
    },
    "{\"min_escape_time\": 130, \"min_market_pnl\": 36.0, \"start_echappee_threshold\": 1.5, \"stop_echappee_threshold\": 1, \"take_profit_market_pnl\": 75.0, \"top_n_threshold\": 1, \"trade_interval_minutes\": 150000, \"trade_value_eur\": 100.0, \"trail_stop_market_pnl\": 40}": {
        "total_pnl": 444.4446240067482,
        "total_invested_capital": 7894.584450162947,
        "total_roi": 5.629740574851596,
        "daily_pnl_std": 18.055449747211448,
        "positive_or_zero_pnl_days": 22,
        "negative_pnl_days": 2
    },
    "{\"min_escape_time\": 135, \"min_market_pnl\": 36.0, \"start_echappee_threshold\": 1.5, \"stop_echappee_threshold\": 1, \"take_profit_market_pnl\": 75.0, \"top_n_threshold\": 1, \"trade_interval_minutes\": 150000, \"trade_value_eur\": 100.0, \"trail_stop_market_pnl\": 40}": {
        "total_pnl": 439.93143847584724,
        "total_invested_capital": 7910.647533759475,
        "total_roi": 5.561256984316342,
        "daily_pnl_std": 17.304923780693713,
        "positive_or_zero_pnl_days": 22,
        "negative_pnl_days": 2
    },
    "{\"min_escape_time\": 60.0, \"min_market_pnl\": 20.0, \"start_echappee_threshold\": 1.5, \"stop_echappee_threshold\": 1, \"take_profit_market_pnl\": 75.0, \"top_n_threshold\": 1, \"trade_interval_minutes\": 150000, \"trade_value_eur\": 100.0, \"trail_stop_market_pnl\": 40}": {
        "total_pnl": 369.8943353816867,
        "total_invested_capital": 10593.638084605336,
        "total_roi": 3.491664831548444,
        "daily_pnl_std": 29.893071558226627,
        "positive_or_zero_pnl_days": 17,
        "negative_pnl_days": 7
    },
    "{\"min_escape_time\": 60.0, \"min_market_pnl\": 21.0, \"start_echappee_threshold\": 1.5, \"stop_echappee_threshold\": 1, \"take_profit_market_pnl\": 75.0, \"top_n_threshold\": 1, \"trade_interval_minutes\": 150000, \"trade_value_eur\": 100.0, \"trail_stop_market_pnl\": 40}": {
        "total_pnl": 369.8943353816867,
        "total_invested_capital": 10593.638084605336,
        "total_roi": 3.491664831548444,
        "daily_pnl_std": 29.893071558226627,
        "positive_or_zero_pnl_days": 17,
        "negative_pnl_days": 7
    },
    "{\"min_escape_time\": 60.0, \"min_market_pnl\": 22.0, \"start_echappee_threshold\": 1.5, \"stop_echappee_threshold\": 1, \"take_profit_market_pnl\": 75.0, \"top_n_threshold\": 1, \"trade_interval_minutes\": 150000, \"trade_value_eur\": 100.0, \"trail_stop_market_pnl\": 40}": {
        "total_pnl": 369.8943353816867,
        "total_invested_capital": 10593.638084605336,
        "total_roi": 3.491664831548444,
        "daily_pnl_std": 29.893071558226627,
        "positive_or_zero_pnl_days": 17,
        "negative_pnl_days": 7
    },
    "{\"min_escape_time\": 60.0, \"min_market_pnl\": 23.0, \"start_echappee_threshold\": 1.5, \"stop_echappee_threshold\": 1, \"take_profit_market_pnl\": 75.0, \"top_n_threshold\": 1, \"trade_interval_minutes\": 150000, \"trade_value_eur\": 100.0, \"trail_stop_market_pnl\": 40}": {
        "total_pnl": 369.8943353816867,
        "total_invested_capital": 10593.638084605336,
        "total_roi": 3.491664831548444,
        "daily_pnl_std": 29.893071558226627,
        "positive_or_zero_pnl_days": 17,
        "negative_pnl_days": 7
    },
    "{\"min_escape_time\": 60.0, \"min_market_pnl\": 24.0, \"start_echappee_threshold\": 1.5, \"stop_echappee_threshold\": 1, \"take_profit_market_pnl\": 75.0, \"top_n_threshold\": 1, \"trade_interval_minutes\": 150000, \"trade_value_eur\": 100.0, \"trail_stop_market_pnl\": 40}": {
        "total_pnl": 372.554332844913,
        "total_invested_capital": 10494.078088954091,
        "total_roi": 3.5501387514645812,
        "daily_pnl_std": 29.97836475888869,
        "positive_or_zero_pnl_days": 17,
        "negative_pnl_days": 7
    },
    "{\"min_escape_time\": 60.0, \"min_market_pnl\": 25.0, \"start_echappee_threshold\": 1.5, \"stop_echappee_threshold\": 1, \"take_profit_market_pnl\": 75.0, \"top_n_threshold\": 1, \"trade_interval_minutes\": 150000, \"trade_value_eur\": 100.0, \"trail_stop_market_pnl\": 40}": {
        "total_pnl": 362.5535355731845,
        "total_invested_capital": 10504.07888622582,
        "total_roi": 3.451550007384343,
        "daily_pnl_std": 30.039331107652234,
        "positive_or_zero_pnl_days": 17,
        "negative_pnl_days": 7
    },
    "{\"min_escape_time\": 60.0, \"min_market_pnl\": 26.0, \"start_echappee_threshold\": 1.5, \"stop_echappee_threshold\": 1, \"take_profit_market_pnl\": 75.0, \"top_n_threshold\": 1, \"trade_interval_minutes\": 150000, \"trade_value_eur\": 100.0, \"trail_stop_market_pnl\": 40}": {
        "total_pnl": 345.2531319782138,
        "total_invested_capital": 10496.114989235997,
        "total_roi": 3.2893421264180005,
        "daily_pnl_std": 29.849214456417485,
        "positive_or_zero_pnl_days": 17,
        "negative_pnl_days": 7
    },
    "{\"min_escape_time\": 60.0, \"min_market_pnl\": 27.0, \"start_echappee_threshold\": 1.5, \"stop_echappee_threshold\": 1, \"take_profit_market_pnl\": 75.0, \"top_n_threshold\": 1, \"trade_interval_minutes\": 150000, \"trade_value_eur\": 100.0, \"trail_stop_market_pnl\": 40}": {
        "total_pnl": 409.4811373874545,
        "total_invested_capital": 10402.356988862157,
        "total_roi": 3.936426502434857,
        "daily_pnl_std": 28.054838246374207,
        "positive_or_zero_pnl_days": 19,
        "negative_pnl_days": 5
    },
    "{\"min_escape_time\": 60.0, \"min_market_pnl\": 28.0, \"start_echappee_threshold\": 1.5, \"stop_echappee_threshold\": 1, \"take_profit_market_pnl\": 75.0, \"top_n_threshold\": 1, \"trade_interval_minutes\": 150000, \"trade_value_eur\": 100.0, \"trail_stop_market_pnl\": 40}": {
        "total_pnl": 427.70993184298277,
        "total_invested_capital": 10204.434197977185,
        "total_roi": 4.191412512883539,
        "daily_pnl_std": 27.850225148630386,
        "positive_or_zero_pnl_days": 20,
        "negative_pnl_days": 4
    },
    "{\"min_escape_time\": 60.0, \"min_market_pnl\": 29.0, \"start_echappee_threshold\": 1.5, \"stop_echappee_threshold\": 1, \"take_profit_market_pnl\": 75.0, \"top_n_threshold\": 1, \"trade_interval_minutes\": 150000, \"trade_value_eur\": 100.0, \"trail_stop_market_pnl\": 40}": {
        "total_pnl": 500.4302230402827,
        "total_invested_capital": 9918.7472987324,
        "total_roi": 5.04529662837803,
        "daily_pnl_std": 26.099880169449648,
        "positive_or_zero_pnl_days": 20,
        "negative_pnl_days": 4
    },
    "{\"min_escape_time\": 60.0, \"min_market_pnl\": 30.0, \"start_echappee_threshold\": 1.5, \"stop_echappee_threshold\": 1, \"take_profit_market_pnl\": 75.0, \"top_n_threshold\": 1, \"trade_interval_minutes\": 150000, \"trade_value_eur\": 100.0, \"trail_stop_market_pnl\": 40}": {
        "total_pnl": 531.8059054538608,
        "total_invested_capital": 9916.832119062543,
        "total_roi": 5.362659154344274,
        "daily_pnl_std": 24.267417962453145,
        "positive_or_zero_pnl_days": 21,
        "negative_pnl_days": 3
    },
    "{\"min_escape_time\": 60.0, \"min_market_pnl\": 31.0, \"start_echappee_threshold\": 1.5, \"stop_echappee_threshold\": 1, \"take_profit_market_pnl\": 75.0, \"top_n_threshold\": 1, \"trade_interval_minutes\": 150000, \"trade_value_eur\": 100.0, \"trail_stop_market_pnl\": 40}": {
        "total_pnl": 524.1266261562705,
        "total_invested_capital": 9914.920398250222,
        "total_roi": 5.2862413928080345,
        "daily_pnl_std": 24.41358318335702,
        "positive_or_zero_pnl_days": 21,
        "negative_pnl_days": 3
    },
    "{\"min_escape_time\": 60.0, \"min_market_pnl\": 32.0, \"start_echappee_threshold\": 1.5, \"stop_echappee_threshold\": 1, \"take_profit_market_pnl\": 75.0, \"top_n_threshold\": 1, \"trade_interval_minutes\": 150000, \"trade_value_eur\": 100.0, \"trail_stop_market_pnl\": 40}": {
        "total_pnl": 541.5282322391868,
        "total_invested_capital": 9619.854091957211,
        "total_roi": 5.629276983441335,
        "daily_pnl_std": 25.33164885140379,
        "positive_or_zero_pnl_days": 20,
        "negative_pnl_days": 4
    },
    "{\"min_escape_time\": 60.0, \"min_market_pnl\": 33.0, \"start_echappee_threshold\": 1.5, \"stop_echappee_threshold\": 1, \"take_profit_market_pnl\": 75.0, \"top_n_threshold\": 1, \"trade_interval_minutes\": 150000, \"trade_value_eur\": 100.0, \"trail_stop_market_pnl\": 40}": {
        "total_pnl": 507.34123369306326,
        "total_invested_capital": 9224.537985756993,
        "total_roi": 5.499909420682269,
        "daily_pnl_std": 22.12316369404944,
        "positive_or_zero_pnl_days": 21,
        "negative_pnl_days": 3
    },
    "{\"min_escape_time\": 60.0, \"min_market_pnl\": 34.0, \"start_echappee_threshold\": 1.5, \"stop_echappee_threshold\": 1, \"take_profit_market_pnl\": 75.0, \"top_n_threshold\": 1, \"trade_interval_minutes\": 150000, \"trade_value_eur\": 100.0, \"trail_stop_market_pnl\": 40}": {
        "total_pnl": 501.5710379704833,
        "total_invested_capital": 9142.994281604886,
        "total_roi": 5.485850942503725,
        "daily_pnl_std": 20.769244599537952,
        "positive_or_zero_pnl_days": 21,
        "negative_pnl_days": 3
    },
    "{\"min_escape_time\": 60.0, \"min_market_pnl\": 35.0, \"start_echappee_threshold\": 1.5, \"stop_echappee_threshold\": 1, \"take_profit_market_pnl\": 75.0, \"top_n_threshold\": 1, \"trade_interval_minutes\": 150000, \"trade_value_eur\": 100.0, \"trail_stop_market_pnl\": 40}": {
        "total_pnl": 485.77214043587446,
        "total_invested_capital": 9148.171579167247,
        "total_roi": 5.3100462341797705,
        "daily_pnl_std": 20.738237419363784,
        "positive_or_zero_pnl_days": 21,
        "negative_pnl_days": 3
    },
    "{\"min_escape_time\": 60.0, \"min_market_pnl\": 36.0, \"start_echappee_threshold\": 1.5, \"stop_echappee_threshold\": 1, \"take_profit_market_pnl\": 75.0, \"top_n_threshold\": 1, \"trade_interval_minutes\": 150000, \"trade_value_eur\": 100.0, \"trail_stop_market_pnl\": 40}": {
        "total_pnl": 579.9951296076179,
        "total_invested_capital": 8562.63459457457,
        "total_roi": 6.773559273160068,
        "daily_pnl_std": 19.010211946176252,
        "positive_or_zero_pnl_days": 22,
        "negative_pnl_days": 2
    },
    "{\"min_escape_time\": 60.0, \"min_market_pnl\": 37.0, \"start_echappee_threshold\": 1.5, \"stop_echappee_threshold\": 1, \"take_profit_market_pnl\": 75.0, \"top_n_threshold\": 1, \"trade_interval_minutes\": 150000, \"trade_value_eur\": 100.0, \"trail_stop_market_pnl\": 40}": {
        "total_pnl": 561.938530229032,
        "total_invested_capital": 8380.96529711783,
        "total_roi": 6.704938038847145,
        "daily_pnl_std": 19.62403538628616,
        "positive_or_zero_pnl_days": 22,
        "negative_pnl_days": 2
    },
    "{\"min_escape_time\": 60.0, \"min_market_pnl\": 38.0, \"start_echappee_threshold\": 1.5, \"stop_echappee_threshold\": 1, \"take_profit_market_pnl\": 75.0, \"top_n_threshold\": 1, \"trade_interval_minutes\": 150000, \"trade_value_eur\": 100.0, \"trail_stop_market_pnl\": 40}": {
        "total_pnl": 560.2993434295058,
        "total_invested_capital": 8271.331083610654,
        "total_roi": 6.773992453762598,
        "daily_pnl_std": 17.559769019940113,
        "positive_or_zero_pnl_days": 22,
        "negative_pnl_days": 2
    },
    "{\"min_escape_time\": 60.0, \"min_market_pnl\": 39.0, \"start_echappee_threshold\": 1.5, \"stop_echappee_threshold\": 1, \"take_profit_market_pnl\": 75.0, \"top_n_threshold\": 1, \"trade_interval_minutes\": 150000, \"trade_value_eur\": 100.0, \"trail_stop_market_pnl\": 40}": {
        "total_pnl": 542.1494223698974,
        "total_invested_capital": 8179.294701829553,
        "total_roi": 6.62831505812633,
        "daily_pnl_std": 17.020845488590627,
        "positive_or_zero_pnl_days": 22,
        "negative_pnl_days": 2
    },
    "{\"min_escape_time\": 60.0, \"min_market_pnl\": 40.0, \"start_echappee_threshold\": 1.5, \"stop_echappee_threshold\": 1, \"take_profit_market_pnl\": 75.0, \"top_n_threshold\": 1, \"trade_interval_minutes\": 150000, \"trade_value_eur\": 100.0, \"trail_stop_market_pnl\": 40}": {
        "total_pnl": 507.8171544596553,
        "total_invested_capital": 8153.374270513654,
        "total_roi": 6.228306681519029,
        "daily_pnl_std": 17.024442048933754,
        "positive_or_zero_pnl_days": 22,
        "negative_pnl_days": 2
    },
    "{\"min_escape_time\": 60.0, \"min_market_pnl\": 41.0, \"start_echappee_threshold\": 1.5, \"stop_echappee_threshold\": 1, \"take_profit_market_pnl\": 75.0, \"top_n_threshold\": 1, \"trade_interval_minutes\": 150000, \"trade_value_eur\": 100.0, \"trail_stop_market_pnl\": 40}": {
        "total_pnl": 496.29443960636854,
        "total_invested_capital": 8054.665082290769,
        "total_roi": 6.161577601749532,
        "daily_pnl_std": 17.374879824165355,
        "positive_or_zero_pnl_days": 22,
        "negative_pnl_days": 2
    },
    "{\"min_escape_time\": 60.0, \"min_market_pnl\": 42.0, \"start_echappee_threshold\": 1.5, \"stop_echappee_threshold\": 1, \"take_profit_market_pnl\": 75.0, \"top_n_threshold\": 1, \"trade_interval_minutes\": 150000, \"trade_value_eur\": 100.0, \"trail_stop_market_pnl\": 40}": {
        "total_pnl": 485.7258467003703,
        "total_invested_capital": 7956.864278271794,
        "total_roi": 6.10448827217986,
        "daily_pnl_std": 16.056073328957634,
        "positive_or_zero_pnl_days": 23,
        "negative_pnl_days": 1
    },
    "{\"min_escape_time\": 60.0, \"min_market_pnl\": 43.0, \"start_echappee_threshold\": 1.5, \"stop_echappee_threshold\": 1, \"take_profit_market_pnl\": 75.0, \"top_n_threshold\": 1, \"trade_interval_minutes\": 150000, \"trade_value_eur\": 100.0, \"trail_stop_market_pnl\": 40}": {
        "total_pnl": 463.02135460823774,
        "total_invested_capital": 7961.530270591378,
        "total_roi": 5.8157331426417445,
        "daily_pnl_std": 16.21605794849503,
        "positive_or_zero_pnl_days": 22,
        "negative_pnl_days": 2
    },
    "{\"min_escape_time\": 60.0, \"min_market_pnl\": 44.0, \"start_echappee_threshold\": 1.5, \"stop_echappee_threshold\": 1, \"take_profit_market_pnl\": 75.0, \"top_n_threshold\": 1, \"trade_interval_minutes\": 150000, \"trade_value_eur\": 100.0, \"trail_stop_market_pnl\": 40}": {
        "total_pnl": 436.5234297141433,
        "total_invested_capital": 7868.328390970826,
        "total_roi": 5.547854741485736,
        "daily_pnl_std": 14.087277188997861,
        "positive_or_zero_pnl_days": 23,
        "negative_pnl_days": 1
    },
    "{\"min_escape_time\": 60.0, \"min_market_pnl\": 45.0, \"start_echappee_threshold\": 1.5, \"stop_echappee_threshold\": 1, \"take_profit_market_pnl\": 75.0, \"top_n_threshold\": 1, \"trade_interval_minutes\": 150000, \"trade_value_eur\": 100.0, \"trail_stop_market_pnl\": 40}": {
        "total_pnl": 430.62930776923895,
        "total_invested_capital": 7771.007909968495,
        "total_roi": 5.541485901936043,
        "daily_pnl_std": 15.145144694107088,
        "positive_or_zero_pnl_days": 23,
        "negative_pnl_days": 1
    },
    "{\"min_escape_time\": 60.0, \"min_market_pnl\": 46.0, \"start_echappee_threshold\": 1.5, \"stop_echappee_threshold\": 1, \"take_profit_market_pnl\": 75.0, \"top_n_threshold\": 1, \"trade_interval_minutes\": 150000, \"trade_value_eur\": 100.0, \"trail_stop_market_pnl\": 40}": {
        "total_pnl": 411.5180450901389,
        "total_invested_capital": 7677.344173982739,
        "total_roi": 5.3601614798605235,
        "daily_pnl_std": 15.25823291171962,
        "positive_or_zero_pnl_days": 23,
        "negative_pnl_days": 1
    },
    "{\"min_escape_time\": 60.0, \"min_market_pnl\": 47.0, \"start_echappee_threshold\": 1.5, \"stop_echappee_threshold\": 1, \"take_profit_market_pnl\": 75.0, \"top_n_threshold\": 1, \"trade_interval_minutes\": 150000, \"trade_value_eur\": 100.0, \"trail_stop_market_pnl\": 40}": {
        "total_pnl": 386.6142431721091,
        "total_invested_capital": 7566.571474984288,
        "total_roi": 5.109503616668234,
        "daily_pnl_std": 14.658499828515556,
        "positive_or_zero_pnl_days": 23,
        "negative_pnl_days": 1
    },
    "{\"min_escape_time\": 60.0, \"min_market_pnl\": 48.0, \"start_echappee_threshold\": 1.5, \"stop_echappee_threshold\": 1, \"take_profit_market_pnl\": 75.0, \"top_n_threshold\": 1, \"trade_interval_minutes\": 150000, \"trade_value_eur\": 100.0, \"trail_stop_market_pnl\": 40}": {
        "total_pnl": 398.0776340588927,
        "total_invested_capital": 7073.804081633687,
        "total_roi": 5.627490236723621,
        "daily_pnl_std": 13.722374024326346,
        "positive_or_zero_pnl_days": 24,
        "negative_pnl_days": 0
    },
    "{\"min_escape_time\": 60.0, \"min_market_pnl\": 49.0, \"start_echappee_threshold\": 1.5, \"stop_echappee_threshold\": 1, \"take_profit_market_pnl\": 75.0, \"top_n_threshold\": 1, \"trade_interval_minutes\": 150000, \"trade_value_eur\": 100.0, \"trail_stop_market_pnl\": 40}": {
        "total_pnl": 391.52659031003714,
        "total_invested_capital": 6970.158125832677,
        "total_roi": 5.617183760278956,
        "daily_pnl_std": 13.35582876107724,
        "positive_or_zero_pnl_days": 24,
        "negative_pnl_days": 0
    },
    "{\"min_escape_time\": 60.0, \"min_market_pnl\": 50.0, \"start_echappee_threshold\": 1.5, \"stop_echappee_threshold\": 1, \"take_profit_market_pnl\": 75.0, \"top_n_threshold\": 1, \"trade_interval_minutes\": 150000, \"trade_value_eur\": 100.0, \"trail_stop_market_pnl\": 40}": {
        "total_pnl": 370.3968426808715,
        "total_invested_capital": 6946.996873691678,
        "total_roi": 5.331754849114252,
        "daily_pnl_std": 12.522108595361066,
        "positive_or_zero_pnl_days": 24,
        "negative_pnl_days": 0
    },
    "{\"min_escape_time\": 60.0, \"min_market_pnl\": 51.0, \"start_echappee_threshold\": 1.5, \"stop_echappee_threshold\": 1, \"take_profit_market_pnl\": 75.0, \"top_n_threshold\": 1, \"trade_interval_minutes\": 150000, \"trade_value_eur\": 100.0, \"trail_stop_market_pnl\": 40}": {
        "total_pnl": 348.3503331169486,
        "total_invested_capital": 6944.97548379004,
        "total_roi": 5.015861235651842,
        "daily_pnl_std": 12.60192249849551,
        "positive_or_zero_pnl_days": 24,
        "negative_pnl_days": 0
    },
    "{\"min_escape_time\": 60.0, \"min_market_pnl\": 52.0, \"start_echappee_threshold\": 1.5, \"stop_echappee_threshold\": 1, \"take_profit_market_pnl\": 75.0, \"top_n_threshold\": 1, \"trade_interval_minutes\": 150000, \"trade_value_eur\": 100.0, \"trail_stop_market_pnl\": 40}": {
        "total_pnl": 305.82643695920706,
        "total_invested_capital": 6937.423378542066,
        "total_roi": 4.408357689472283,
        "daily_pnl_std": 11.415476008692591,
        "positive_or_zero_pnl_days": 24,
        "negative_pnl_days": 0
    },
    "{\"min_escape_time\": 60.0, \"min_market_pnl\": 53.0, \"start_echappee_threshold\": 1.5, \"stop_echappee_threshold\": 1, \"take_profit_market_pnl\": 75.0, \"top_n_threshold\": 1, \"trade_interval_minutes\": 150000, \"trade_value_eur\": 100.0, \"trail_stop_market_pnl\": 40}": {
        "total_pnl": 301.0595211908221,
        "total_invested_capital": 6844.597694545984,
        "total_roi": 4.398498416213957,
        "daily_pnl_std": 11.852698953493976,
        "positive_or_zero_pnl_days": 22,
        "negative_pnl_days": 2
    },
    "{\"min_escape_time\": 60.0, \"min_market_pnl\": 54.0, \"start_echappee_threshold\": 1.5, \"stop_echappee_threshold\": 1, \"take_profit_market_pnl\": 75.0, \"top_n_threshold\": 1, \"trade_interval_minutes\": 150000, \"trade_value_eur\": 100.0, \"trail_stop_market_pnl\": 40}": {
        "total_pnl": 259.3137282729149,
        "total_invested_capital": 6854.573287419975,
        "total_roi": 3.7830761653511944,
        "daily_pnl_std": 11.882583290409643,
        "positive_or_zero_pnl_days": 20,
        "negative_pnl_days": 4
    },
    "{\"min_escape_time\": 60.0, \"min_market_pnl\": 55.0, \"start_echappee_threshold\": 1.5, \"stop_echappee_threshold\": 1, \"take_profit_market_pnl\": 75.0, \"top_n_threshold\": 1, \"trade_interval_minutes\": 150000, \"trade_value_eur\": 100.0, \"trail_stop_market_pnl\": 40}": {
        "total_pnl": 264.6616801172495,
        "total_invested_capital": 6644.044783361256,
        "total_roi": 3.9834421462667478,
        "daily_pnl_std": 11.366139745114252,
        "positive_or_zero_pnl_days": 20,
        "negative_pnl_days": 4
    },
    "{\"min_escape_time\": 60.0, \"min_market_pnl\": 56.0, \"start_echappee_threshold\": 1.5, \"stop_echappee_threshold\": 1, \"take_profit_market_pnl\": 75.0, \"top_n_threshold\": 1, \"trade_interval_minutes\": 150000, \"trade_value_eur\": 100.0, \"trail_stop_market_pnl\": 40}": {
        "total_pnl": 243.62607271969318,
        "total_invested_capital": 6550.403387852013,
        "total_roi": 3.719252972595666,
        "daily_pnl_std": 10.943309790017679,
        "positive_or_zero_pnl_days": 20,
        "negative_pnl_days": 4
    },
    "{\"min_escape_time\": 60.0, \"min_market_pnl\": 57.0, \"start_echappee_threshold\": 1.5, \"stop_echappee_threshold\": 1, \"take_profit_market_pnl\": 75.0, \"top_n_threshold\": 1, \"trade_interval_minutes\": 150000, \"trade_value_eur\": 100.0, \"trail_stop_market_pnl\": 40}": {
        "total_pnl": 240.96866358816624,
        "total_invested_capital": 6369.897403128445,
        "total_roi": 3.782928489080835,
        "daily_pnl_std": 10.817059665721121,
        "positive_or_zero_pnl_days": 21,
        "negative_pnl_days": 3
    },
    "{\"min_escape_time\": 60.0, \"min_market_pnl\": 58.0, \"start_echappee_threshold\": 1.5, \"stop_echappee_threshold\": 1, \"take_profit_market_pnl\": 75.0, \"top_n_threshold\": 1, \"trade_interval_minutes\": 150000, \"trade_value_eur\": 100.0, \"trail_stop_market_pnl\": 40}": {
        "total_pnl": 215.31124909222126,
        "total_invested_capital": 6370.81381649524,
        "total_roi": 3.379650626969192,
        "daily_pnl_std": 11.612965452734318,
        "positive_or_zero_pnl_days": 20,
        "negative_pnl_days": 4
    },
    "{\"min_escape_time\": 60.0, \"min_market_pnl\": 59.0, \"start_echappee_threshold\": 1.5, \"stop_echappee_threshold\": 1, \"take_profit_market_pnl\": 75.0, \"top_n_threshold\": 1, \"trade_interval_minutes\": 150000, \"trade_value_eur\": 100.0, \"trail_stop_market_pnl\": 40}": {
        "total_pnl": 197.21679539978504,
        "total_invested_capital": 6275.098272271454,
        "total_roi": 3.142847917956139,
        "daily_pnl_std": 11.819683528079665,
        "positive_or_zero_pnl_days": 20,
        "negative_pnl_days": 4
    },
    "{\"min_escape_time\": 60.0, \"min_market_pnl\": 60.0, \"start_echappee_threshold\": 1.5, \"stop_echappee_threshold\": 1, \"take_profit_market_pnl\": 75.0, \"top_n_threshold\": 1, \"trade_interval_minutes\": 150000, \"trade_value_eur\": 100.0, \"trail_stop_market_pnl\": 40}": {
        "total_pnl": 177.79718409478664,
        "total_invested_capital": 6075.673831768334,
        "total_roi": 2.9263780284768597,
        "daily_pnl_std": 11.755415078724598,
        "positive_or_zero_pnl_days": 19,
        "negative_pnl_days": 5
    },
    "{\"min_escape_time\": 60.0, \"min_market_pnl\": 61.0, \"start_echappee_threshold\": 1.5, \"stop_echappee_threshold\": 1, \"take_profit_market_pnl\": 75.0, \"top_n_threshold\": 1, \"trade_interval_minutes\": 150000, \"trade_value_eur\": 100.0, \"trail_stop_market_pnl\": 40}": {
        "total_pnl": 176.93469668924809,
        "total_invested_capital": 5994.276319749653,
        "total_roi": 2.951727402126795,
        "daily_pnl_std": 11.792422598106569,
        "positive_or_zero_pnl_days": 17,
        "negative_pnl_days": 7
    },
    "{\"min_escape_time\": 60.0, \"min_market_pnl\": 62.0, \"start_echappee_threshold\": 1.5, \"stop_echappee_threshold\": 1, \"take_profit_market_pnl\": 75.0, \"top_n_threshold\": 1, \"trade_interval_minutes\": 150000, \"trade_value_eur\": 100.0, \"trail_stop_market_pnl\": 40}": {
        "total_pnl": 168.77489818632603,
        "total_invested_capital": 5897.284221895039,
        "total_roi": 2.861908835251826,
        "daily_pnl_std": 11.84933803437964,
        "positive_or_zero_pnl_days": 17,
        "negative_pnl_days": 7
    },
    "{\"min_escape_time\": 60.0, \"min_market_pnl\": 63.0, \"start_echappee_threshold\": 1.5, \"stop_echappee_threshold\": 1, \"take_profit_market_pnl\": 75.0, \"top_n_threshold\": 1, \"trade_interval_minutes\": 150000, \"trade_value_eur\": 100.0, \"trail_stop_market_pnl\": 40}": {
        "total_pnl": 191.99314673244953,
        "total_invested_capital": 5695.9210692718625,
        "total_roi": 3.370712908368882,
        "daily_pnl_std": 10.755436280339953,
        "positive_or_zero_pnl_days": 19,
        "negative_pnl_days": 5
    },
    "{\"min_escape_time\": 60.0, \"min_market_pnl\": 64.0, \"start_echappee_threshold\": 1.5, \"stop_echappee_threshold\": 1, \"take_profit_market_pnl\": 75.0, \"top_n_threshold\": 1, \"trade_interval_minutes\": 150000, \"trade_value_eur\": 100.0, \"trail_stop_market_pnl\": 40}": {
        "total_pnl": 160.08444985747337,
        "total_invested_capital": 5691.777266122401,
        "total_roi": 2.8125564717772775,
        "daily_pnl_std": 9.762126143417293,
        "positive_or_zero_pnl_days": 19,
        "negative_pnl_days": 5
    },
    "{\"min_escape_time\": 60.0, \"min_market_pnl\": 65.0, \"start_echappee_threshold\": 1.5, \"stop_echappee_threshold\": 1, \"take_profit_market_pnl\": 75.0, \"top_n_threshold\": 1, \"trade_interval_minutes\": 150000, \"trade_value_eur\": 100.0, \"trail_stop_market_pnl\": 40}": {
        "total_pnl": 124.01943013072014,
        "total_invested_capital": 5691.932184197009,
        "total_roi": 2.1788634529948503,
        "daily_pnl_std": 9.324022747760754,
        "positive_or_zero_pnl_days": 19,
        "negative_pnl_days": 5
    },
    "{\"min_escape_time\": 60.0, \"min_market_pnl\": 66.0, \"start_echappee_threshold\": 1.5, \"stop_echappee_threshold\": 1, \"take_profit_market_pnl\": 75.0, \"top_n_threshold\": 1, \"trade_interval_minutes\": 150000, \"trade_value_eur\": 100.0, \"trail_stop_market_pnl\": 40}": {
        "total_pnl": 133.98642525076866,
        "total_invested_capital": 5403.343192256987,
        "total_roi": 2.479694894130948,
        "daily_pnl_std": 7.647867454579954,
        "positive_or_zero_pnl_days": 20,
        "negative_pnl_days": 4
    },
    "{\"min_escape_time\": 60.0, \"min_market_pnl\": 67.0, \"start_echappee_threshold\": 1.5, \"stop_echappee_threshold\": 1, \"take_profit_market_pnl\": 75.0, \"top_n_threshold\": 1, \"trade_interval_minutes\": 150000, \"trade_value_eur\": 100.0, \"trail_stop_market_pnl\": 40}": {
        "total_pnl": 120.5479447543621,
        "total_invested_capital": 5299.260272778571,
        "total_roi": 2.2748070211534444,
        "daily_pnl_std": 6.379104761150074,
        "positive_or_zero_pnl_days": 21,
        "negative_pnl_days": 3
    },
    "{\"min_escape_time\": 60.0, \"min_market_pnl\": 68.0, \"start_echappee_threshold\": 1.5, \"stop_echappee_threshold\": 1, \"take_profit_market_pnl\": 75.0, \"top_n_threshold\": 1, \"trade_interval_minutes\": 150000, \"trade_value_eur\": 100.0, \"trail_stop_market_pnl\": 40}": {
        "total_pnl": 130.215750426054,
        "total_invested_capital": 5204.242468394339,
        "total_roi": 2.5021076788189958,
        "daily_pnl_std": 6.153726860928477,
        "positive_or_zero_pnl_days": 22,
        "negative_pnl_days": 2
    },
    "{\"min_escape_time\": 60.0, \"min_market_pnl\": 69.0, \"start_echappee_threshold\": 1.5, \"stop_echappee_threshold\": 1, \"take_profit_market_pnl\": 75.0, \"top_n_threshold\": 1, \"trade_interval_minutes\": 150000, \"trade_value_eur\": 100.0, \"trail_stop_market_pnl\": 40}": {
        "total_pnl": 137.49160513281822,
        "total_invested_capital": 5113.469114042819,
        "total_roi": 2.6888126644831614,
        "daily_pnl_std": 4.390680465579416,
        "positive_or_zero_pnl_days": 23,
        "negative_pnl_days": 1
    },
    "{\"min_escape_time\": 60, \"min_market_pnl\": 23.0, \"start_echappee_threshold\": 1.5, \"stop_echappee_threshold\": 1.0, \"take_profit_market_pnl\": 75.0, \"top_n_threshold\": 1, \"trade_interval_minutes\": 150000, \"trade_value_eur\": 100.0, \"trail_stop_market_pnl\": 40.0}": {
        "total_pnl": 369.8943353816867,
        "total_invested_capital": 10593.638084605336,
        "total_roi": 3.491664831548444,
        "daily_pnl_std": 29.893071558226627,
        "positive_or_zero_pnl_days": 17,
        "negative_pnl_days": 7
    },
    "{\"min_escape_time\": 60, \"min_market_pnl\": 20.0, \"start_echappee_threshold\": 1.5, \"stop_echappee_threshold\": 1.0, \"take_profit_market_pnl\": 75.0, \"top_n_threshold\": 1, \"trade_interval_minutes\": 150000, \"trade_value_eur\": 100.0, \"trail_stop_market_pnl\": 40.0}": {
        "total_pnl": 369.8943353816867,
        "total_invested_capital": 10593.638084605336,
        "total_roi": 3.491664831548444,
        "daily_pnl_std": 29.893071558226627,
        "positive_or_zero_pnl_days": 17,
        "negative_pnl_days": 7
    },
    "{\"min_escape_time\": 60, \"min_market_pnl\": 21.0, \"start_echappee_threshold\": 1.5, \"stop_echappee_threshold\": 1.0, \"take_profit_market_pnl\": 75.0, \"top_n_threshold\": 1, \"trade_interval_minutes\": 150000, \"trade_value_eur\": 100.0, \"trail_stop_market_pnl\": 40.0}": {
        "total_pnl": 369.8943353816867,
        "total_invested_capital": 10593.638084605336,
        "total_roi": 3.491664831548444,
        "daily_pnl_std": 29.893071558226627,
        "positive_or_zero_pnl_days": 17,
        "negative_pnl_days": 7
    },
    "{\"min_escape_time\": 60, \"min_market_pnl\": 22.0, \"start_echappee_threshold\": 1.5, \"stop_echappee_threshold\": 1.0, \"take_profit_market_pnl\": 75.0, \"top_n_threshold\": 1, \"trade_interval_minutes\": 150000, \"trade_value_eur\": 100.0, \"trail_stop_market_pnl\": 40.0}": {
        "total_pnl": 369.8943353816867,
        "total_invested_capital": 10593.638084605336,
        "total_roi": 3.491664831548444,
        "daily_pnl_std": 29.893071558226627,
        "positive_or_zero_pnl_days": 17,
        "negative_pnl_days": 7
    },
    "{\"min_escape_time\": 60, \"min_market_pnl\": 24.0, \"start_echappee_threshold\": 1.5, \"stop_echappee_threshold\": 1.0, \"take_profit_market_pnl\": 75.0, \"top_n_threshold\": 1, \"trade_interval_minutes\": 150000, \"trade_value_eur\": 100.0, \"trail_stop_market_pnl\": 40.0}": {
        "total_pnl": 372.554332844913,
        "total_invested_capital": 10494.078088954091,
        "total_roi": 3.5501387514645812,
        "daily_pnl_std": 29.97836475888869,
        "positive_or_zero_pnl_days": 17,
        "negative_pnl_days": 7
    },
    "{\"min_escape_time\": 60, \"min_market_pnl\": 25.0, \"start_echappee_threshold\": 1.5, \"stop_echappee_threshold\": 1.0, \"take_profit_market_pnl\": 75.0, \"top_n_threshold\": 1, \"trade_interval_minutes\": 150000, \"trade_value_eur\": 100.0, \"trail_stop_market_pnl\": 40.0}": {
        "total_pnl": 362.5535355731845,
        "total_invested_capital": 10504.07888622582,
        "total_roi": 3.451550007384343,
        "daily_pnl_std": 30.039331107652234,
        "positive_or_zero_pnl_days": 17,
        "negative_pnl_days": 7
    },
    "{\"min_escape_time\": 60, \"min_market_pnl\": 26.0, \"start_echappee_threshold\": 1.5, \"stop_echappee_threshold\": 1.0, \"take_profit_market_pnl\": 75.0, \"top_n_threshold\": 1, \"trade_interval_minutes\": 150000, \"trade_value_eur\": 100.0, \"trail_stop_market_pnl\": 40.0}": {
        "total_pnl": 345.2531319782138,
        "total_invested_capital": 10496.114989235997,
        "total_roi": 3.2893421264180005,
        "daily_pnl_std": 29.849214456417485,
        "positive_or_zero_pnl_days": 17,
        "negative_pnl_days": 7
    },
    "{\"min_escape_time\": 60, \"min_market_pnl\": 27.0, \"start_echappee_threshold\": 1.5, \"stop_echappee_threshold\": 1.0, \"take_profit_market_pnl\": 75.0, \"top_n_threshold\": 1, \"trade_interval_minutes\": 150000, \"trade_value_eur\": 100.0, \"trail_stop_market_pnl\": 40.0}": {
        "total_pnl": 409.4811373874545,
        "total_invested_capital": 10402.356988862157,
        "total_roi": 3.936426502434857,
        "daily_pnl_std": 28.054838246374207,
        "positive_or_zero_pnl_days": 19,
        "negative_pnl_days": 5
    },
    "{\"min_escape_time\": 60, \"min_market_pnl\": 28.0, \"start_echappee_threshold\": 1.5, \"stop_echappee_threshold\": 1.0, \"take_profit_market_pnl\": 75.0, \"top_n_threshold\": 1, \"trade_interval_minutes\": 150000, \"trade_value_eur\": 100.0, \"trail_stop_market_pnl\": 40.0}": {
        "total_pnl": 427.70993184298277,
        "total_invested_capital": 10204.434197977185,
        "total_roi": 4.191412512883539,
        "daily_pnl_std": 27.850225148630386,
        "positive_or_zero_pnl_days": 20,
        "negative_pnl_days": 4
    },
    "{\"min_escape_time\": 60, \"min_market_pnl\": 29.0, \"start_echappee_threshold\": 1.5, \"stop_echappee_threshold\": 1.0, \"take_profit_market_pnl\": 75.0, \"top_n_threshold\": 1, \"trade_interval_minutes\": 150000, \"trade_value_eur\": 100.0, \"trail_stop_market_pnl\": 40.0}": {
        "total_pnl": 500.4302230402827,
        "total_invested_capital": 9918.7472987324,
        "total_roi": 5.04529662837803,
        "daily_pnl_std": 26.099880169449648,
        "positive_or_zero_pnl_days": 20,
        "negative_pnl_days": 4
    },
    "{\"min_escape_time\": 60, \"min_market_pnl\": 30.0, \"start_echappee_threshold\": 1.5, \"stop_echappee_threshold\": 1.0, \"take_profit_market_pnl\": 75.0, \"top_n_threshold\": 1, \"trade_interval_minutes\": 150000, \"trade_value_eur\": 100.0, \"trail_stop_market_pnl\": 40.0}": {
        "total_pnl": 531.8059054538608,
        "total_invested_capital": 9916.832119062543,
        "total_roi": 5.362659154344274,
        "daily_pnl_std": 24.267417962453145,
        "positive_or_zero_pnl_days": 21,
        "negative_pnl_days": 3
    },
    "{\"min_escape_time\": 60, \"min_market_pnl\": 31.0, \"start_echappee_threshold\": 1.5, \"stop_echappee_threshold\": 1.0, \"take_profit_market_pnl\": 75.0, \"top_n_threshold\": 1, \"trade_interval_minutes\": 150000, \"trade_value_eur\": 100.0, \"trail_stop_market_pnl\": 40.0}": {
        "total_pnl": 524.1266261562705,
        "total_invested_capital": 9914.920398250222,
        "total_roi": 5.2862413928080345,
        "daily_pnl_std": 24.41358318335702,
        "positive_or_zero_pnl_days": 21,
        "negative_pnl_days": 3
    },
    "{\"min_escape_time\": 60, \"min_market_pnl\": 32.0, \"start_echappee_threshold\": 1.5, \"stop_echappee_threshold\": 1.0, \"take_profit_market_pnl\": 75.0, \"top_n_threshold\": 1, \"trade_interval_minutes\": 150000, \"trade_value_eur\": 100.0, \"trail_stop_market_pnl\": 40.0}": {
        "total_pnl": 541.5282322391868,
        "total_invested_capital": 9619.854091957211,
        "total_roi": 5.629276983441335,
        "daily_pnl_std": 25.33164885140379,
        "positive_or_zero_pnl_days": 20,
        "negative_pnl_days": 4
    },
    "{\"min_escape_time\": 60, \"min_market_pnl\": 33.0, \"start_echappee_threshold\": 1.5, \"stop_echappee_threshold\": 1.0, \"take_profit_market_pnl\": 75.0, \"top_n_threshold\": 1, \"trade_interval_minutes\": 150000, \"trade_value_eur\": 100.0, \"trail_stop_market_pnl\": 40.0}": {
        "total_pnl": 507.34123369306326,
        "total_invested_capital": 9224.537985756993,
        "total_roi": 5.499909420682269,
        "daily_pnl_std": 22.12316369404944,
        "positive_or_zero_pnl_days": 21,
        "negative_pnl_days": 3
    },
    "{\"min_escape_time\": 60, \"min_market_pnl\": 34.0, \"start_echappee_threshold\": 1.5, \"stop_echappee_threshold\": 1.0, \"take_profit_market_pnl\": 75.0, \"top_n_threshold\": 1, \"trade_interval_minutes\": 150000, \"trade_value_eur\": 100.0, \"trail_stop_market_pnl\": 40.0}": {
        "total_pnl": 501.5710379704833,
        "total_invested_capital": 9142.994281604886,
        "total_roi": 5.485850942503725,
        "daily_pnl_std": 20.769244599537952,
        "positive_or_zero_pnl_days": 21,
        "negative_pnl_days": 3
    },
    "{\"min_escape_time\": 60, \"min_market_pnl\": 35.0, \"start_echappee_threshold\": 1.5, \"stop_echappee_threshold\": 1.0, \"take_profit_market_pnl\": 75.0, \"top_n_threshold\": 1, \"trade_interval_minutes\": 150000, \"trade_value_eur\": 100.0, \"trail_stop_market_pnl\": 40.0}": {
        "total_pnl": 485.77214043587446,
        "total_invested_capital": 9148.171579167247,
        "total_roi": 5.3100462341797705,
        "daily_pnl_std": 20.738237419363784,
        "positive_or_zero_pnl_days": 21,
        "negative_pnl_days": 3
    },
    "{\"min_escape_time\": 60, \"min_market_pnl\": 36.0, \"start_echappee_threshold\": 1.5, \"stop_echappee_threshold\": 1.0, \"take_profit_market_pnl\": 75.0, \"top_n_threshold\": 1, \"trade_interval_minutes\": 150000, \"trade_value_eur\": 100.0, \"trail_stop_market_pnl\": 40.0}": {
        "total_pnl": 579.9951296076179,
        "total_invested_capital": 8562.63459457457,
        "total_roi": 6.773559273160068,
        "daily_pnl_std": 19.010211946176252,
        "positive_or_zero_pnl_days": 22,
        "negative_pnl_days": 2
    },
    "{\"min_escape_time\": 60, \"min_market_pnl\": 37.0, \"start_echappee_threshold\": 1.5, \"stop_echappee_threshold\": 1.0, \"take_profit_market_pnl\": 75.0, \"top_n_threshold\": 1, \"trade_interval_minutes\": 150000, \"trade_value_eur\": 100.0, \"trail_stop_market_pnl\": 40.0}": {
        "total_pnl": 561.938530229032,
        "total_invested_capital": 8380.96529711783,
        "total_roi": 6.704938038847145,
        "daily_pnl_std": 19.62403538628616,
        "positive_or_zero_pnl_days": 22,
        "negative_pnl_days": 2
    },
    "{\"min_escape_time\": 60, \"min_market_pnl\": 55.0, \"start_echappee_threshold\": 1.5, \"stop_echappee_threshold\": 1.0, \"take_profit_market_pnl\": 75.0, \"top_n_threshold\": 1, \"trade_interval_minutes\": 150000, \"trade_value_eur\": 100.0, \"trail_stop_market_pnl\": 40.0}": {
        "total_pnl": 264.6616801172495,
        "total_invested_capital": 6644.044783361256,
        "total_roi": 3.9834421462667478,
        "daily_pnl_std": 11.366139745114252,
        "positive_or_zero_pnl_days": 20,
        "negative_pnl_days": 4
    },
    "{\"min_escape_time\": 60, \"min_market_pnl\": 38.0, \"start_echappee_threshold\": 1.5, \"stop_echappee_threshold\": 1.0, \"take_profit_market_pnl\": 75.0, \"top_n_threshold\": 1, \"trade_interval_minutes\": 150000, \"trade_value_eur\": 100.0, \"trail_stop_market_pnl\": 40.0}": {
        "total_pnl": 560.2993434295058,
        "total_invested_capital": 8271.331083610654,
        "total_roi": 6.773992453762598,
        "daily_pnl_std": 17.559769019940113,
        "positive_or_zero_pnl_days": 22,
        "negative_pnl_days": 2
    },
    "{\"min_escape_time\": 60, \"min_market_pnl\": 39.0, \"start_echappee_threshold\": 1.5, \"stop_echappee_threshold\": 1.0, \"take_profit_market_pnl\": 75.0, \"top_n_threshold\": 1, \"trade_interval_minutes\": 150000, \"trade_value_eur\": 100.0, \"trail_stop_market_pnl\": 40.0}": {
        "total_pnl": 542.1494223698974,
        "total_invested_capital": 8179.294701829553,
        "total_roi": 6.62831505812633,
        "daily_pnl_std": 17.020845488590627,
        "positive_or_zero_pnl_days": 22,
        "negative_pnl_days": 2
    },
    "{\"min_escape_time\": 60, \"min_market_pnl\": 40.0, \"start_echappee_threshold\": 1.5, \"stop_echappee_threshold\": 1.0, \"take_profit_market_pnl\": 75.0, \"top_n_threshold\": 1, \"trade_interval_minutes\": 150000, \"trade_value_eur\": 100.0, \"trail_stop_market_pnl\": 40.0}": {
        "total_pnl": 507.8171544596553,
        "total_invested_capital": 8153.374270513654,
        "total_roi": 6.228306681519029,
        "daily_pnl_std": 17.024442048933754,
        "positive_or_zero_pnl_days": 22,
        "negative_pnl_days": 2
    },
    "{\"min_escape_time\": 60, \"min_market_pnl\": 41.0, \"start_echappee_threshold\": 1.5, \"stop_echappee_threshold\": 1.0, \"take_profit_market_pnl\": 75.0, \"top_n_threshold\": 1, \"trade_interval_minutes\": 150000, \"trade_value_eur\": 100.0, \"trail_stop_market_pnl\": 40.0}": {
        "total_pnl": 496.29443960636854,
        "total_invested_capital": 8054.665082290769,
        "total_roi": 6.161577601749532,
        "daily_pnl_std": 17.374879824165355,
        "positive_or_zero_pnl_days": 22,
        "negative_pnl_days": 2
    },
    "{\"min_escape_time\": 60, \"min_market_pnl\": 42.0, \"start_echappee_threshold\": 1.5, \"stop_echappee_threshold\": 1.0, \"take_profit_market_pnl\": 75.0, \"top_n_threshold\": 1, \"trade_interval_minutes\": 150000, \"trade_value_eur\": 100.0, \"trail_stop_market_pnl\": 40.0}": {
        "total_pnl": 485.7258467003703,
        "total_invested_capital": 7956.864278271794,
        "total_roi": 6.10448827217986,
        "daily_pnl_std": 16.056073328957634,
        "positive_or_zero_pnl_days": 23,
        "negative_pnl_days": 1
    },
    "{\"min_escape_time\": 60, \"min_market_pnl\": 43.0, \"start_echappee_threshold\": 1.5, \"stop_echappee_threshold\": 1.0, \"take_profit_market_pnl\": 75.0, \"top_n_threshold\": 1, \"trade_interval_minutes\": 150000, \"trade_value_eur\": 100.0, \"trail_stop_market_pnl\": 40.0}": {
        "total_pnl": 463.02135460823774,
        "total_invested_capital": 7961.530270591378,
        "total_roi": 5.8157331426417445,
        "daily_pnl_std": 16.21605794849503,
        "positive_or_zero_pnl_days": 22,
        "negative_pnl_days": 2
    },
    "{\"min_escape_time\": 60, \"min_market_pnl\": 44.0, \"start_echappee_threshold\": 1.5, \"stop_echappee_threshold\": 1.0, \"take_profit_market_pnl\": 75.0, \"top_n_threshold\": 1, \"trade_interval_minutes\": 150000, \"trade_value_eur\": 100.0, \"trail_stop_market_pnl\": 40.0}": {
        "total_pnl": 436.5234297141433,
        "total_invested_capital": 7868.328390970826,
        "total_roi": 5.547854741485736,
        "daily_pnl_std": 14.087277188997861,
        "positive_or_zero_pnl_days": 23,
        "negative_pnl_days": 1
    },
    "{\"min_escape_time\": 60, \"min_market_pnl\": 45.0, \"start_echappee_threshold\": 1.5, \"stop_echappee_threshold\": 1.0, \"take_profit_market_pnl\": 75.0, \"top_n_threshold\": 1, \"trade_interval_minutes\": 150000, \"trade_value_eur\": 100.0, \"trail_stop_market_pnl\": 40.0}": {
        "total_pnl": 430.62930776923895,
        "total_invested_capital": 7771.007909968495,
        "total_roi": 5.541485901936043,
        "daily_pnl_std": 15.145144694107088,
        "positive_or_zero_pnl_days": 23,
        "negative_pnl_days": 1
    },
    "{\"min_escape_time\": 60, \"min_market_pnl\": 46.0, \"start_echappee_threshold\": 1.5, \"stop_echappee_threshold\": 1.0, \"take_profit_market_pnl\": 75.0, \"top_n_threshold\": 1, \"trade_interval_minutes\": 150000, \"trade_value_eur\": 100.0, \"trail_stop_market_pnl\": 40.0}": {
        "total_pnl": 411.5180450901389,
        "total_invested_capital": 7677.344173982739,
        "total_roi": 5.3601614798605235,
        "daily_pnl_std": 15.25823291171962,
        "positive_or_zero_pnl_days": 23,
        "negative_pnl_days": 1
    },
    "{\"min_escape_time\": 60, \"min_market_pnl\": 47.0, \"start_echappee_threshold\": 1.5, \"stop_echappee_threshold\": 1.0, \"take_profit_market_pnl\": 75.0, \"top_n_threshold\": 1, \"trade_interval_minutes\": 150000, \"trade_value_eur\": 100.0, \"trail_stop_market_pnl\": 40.0}": {
        "total_pnl": 386.6142431721091,
        "total_invested_capital": 7566.571474984288,
        "total_roi": 5.109503616668234,
        "daily_pnl_std": 14.658499828515556,
        "positive_or_zero_pnl_days": 23,
        "negative_pnl_days": 1
    },
    "{\"min_escape_time\": 60, \"min_market_pnl\": 48.0, \"start_echappee_threshold\": 1.5, \"stop_echappee_threshold\": 1.0, \"take_profit_market_pnl\": 75.0, \"top_n_threshold\": 1, \"trade_interval_minutes\": 150000, \"trade_value_eur\": 100.0, \"trail_stop_market_pnl\": 40.0}": {
        "total_pnl": 398.0776340588927,
        "total_invested_capital": 7073.804081633687,
        "total_roi": 5.627490236723621,
        "daily_pnl_std": 13.722374024326346,
        "positive_or_zero_pnl_days": 24,
        "negative_pnl_days": 0
    },
    "{\"min_escape_time\": 60, \"min_market_pnl\": 49.0, \"start_echappee_threshold\": 1.5, \"stop_echappee_threshold\": 1.0, \"take_profit_market_pnl\": 75.0, \"top_n_threshold\": 1, \"trade_interval_minutes\": 150000, \"trade_value_eur\": 100.0, \"trail_stop_market_pnl\": 40.0}": {
        "total_pnl": 391.52659031003714,
        "total_invested_capital": 6970.158125832677,
        "total_roi": 5.617183760278956,
        "daily_pnl_std": 13.35582876107724,
        "positive_or_zero_pnl_days": 24,
        "negative_pnl_days": 0
    },
    "{\"min_escape_time\": 60, \"min_market_pnl\": 50.0, \"start_echappee_threshold\": 1.5, \"stop_echappee_threshold\": 1.0, \"take_profit_market_pnl\": 75.0, \"top_n_threshold\": 1, \"trade_interval_minutes\": 150000, \"trade_value_eur\": 100.0, \"trail_stop_market_pnl\": 40.0}": {
        "total_pnl": 370.3968426808715,
        "total_invested_capital": 6946.996873691678,
        "total_roi": 5.331754849114252,
        "daily_pnl_std": 12.522108595361066,
        "positive_or_zero_pnl_days": 24,
        "negative_pnl_days": 0
    },
    "{\"min_escape_time\": 60, \"min_market_pnl\": 51.0, \"start_echappee_threshold\": 1.5, \"stop_echappee_threshold\": 1.0, \"take_profit_market_pnl\": 75.0, \"top_n_threshold\": 1, \"trade_interval_minutes\": 150000, \"trade_value_eur\": 100.0, \"trail_stop_market_pnl\": 40.0}": {
        "total_pnl": 348.3503331169486,
        "total_invested_capital": 6944.97548379004,
        "total_roi": 5.015861235651842,
        "daily_pnl_std": 12.60192249849551,
        "positive_or_zero_pnl_days": 24,
        "negative_pnl_days": 0
    },
    "{\"min_escape_time\": 60, \"min_market_pnl\": 65.0, \"start_echappee_threshold\": 1.5, \"stop_echappee_threshold\": 1.0, \"take_profit_market_pnl\": 75.0, \"top_n_threshold\": 1, \"trade_interval_minutes\": 150000, \"trade_value_eur\": 100.0, \"trail_stop_market_pnl\": 40.0}": {
        "total_pnl": 124.01943013072014,
        "total_invested_capital": 5691.932184197009,
        "total_roi": 2.1788634529948503,
        "daily_pnl_std": 9.324022747760754,
        "positive_or_zero_pnl_days": 19,
        "negative_pnl_days": 5
    },
    "{\"min_escape_time\": 60, \"min_market_pnl\": 52.0, \"start_echappee_threshold\": 1.5, \"stop_echappee_threshold\": 1.0, \"take_profit_market_pnl\": 75.0, \"top_n_threshold\": 1, \"trade_interval_minutes\": 150000, \"trade_value_eur\": 100.0, \"trail_stop_market_pnl\": 40.0}": {
        "total_pnl": 305.82643695920706,
        "total_invested_capital": 6937.423378542066,
        "total_roi": 4.408357689472283,
        "daily_pnl_std": 11.415476008692591,
        "positive_or_zero_pnl_days": 24,
        "negative_pnl_days": 0
    },
    "{\"min_escape_time\": 60, \"min_market_pnl\": 53.0, \"start_echappee_threshold\": 1.5, \"stop_echappee_threshold\": 1.0, \"take_profit_market_pnl\": 75.0, \"top_n_threshold\": 1, \"trade_interval_minutes\": 150000, \"trade_value_eur\": 100.0, \"trail_stop_market_pnl\": 40.0}": {
        "total_pnl": 301.0595211908221,
        "total_invested_capital": 6844.597694545984,
        "total_roi": 4.398498416213957,
        "daily_pnl_std": 11.852698953493976,
        "positive_or_zero_pnl_days": 22,
        "negative_pnl_days": 2
    },
    "{\"min_escape_time\": 60, \"min_market_pnl\": 54.0, \"start_echappee_threshold\": 1.5, \"stop_echappee_threshold\": 1.0, \"take_profit_market_pnl\": 75.0, \"top_n_threshold\": 1, \"trade_interval_minutes\": 150000, \"trade_value_eur\": 100.0, \"trail_stop_market_pnl\": 40.0}": {
        "total_pnl": 259.3137282729149,
        "total_invested_capital": 6854.573287419975,
        "total_roi": 3.7830761653511944,
        "daily_pnl_std": 11.882583290409643,
        "positive_or_zero_pnl_days": 20,
        "negative_pnl_days": 4
    }
}